espec/__init__.py
espec/espec.py
espec/get_version.py
espec/version.py
espec-0.1.0.4.dist-info/LICENSE
espec-0.1.0.4.dist-info/METADATA
espec-0.1.0.4.dist-info/WHEEL
espec-0.1.0.4.dist-info/top_level.txt
espec-0.1.0.4.dist-info/RECORD
