Metadata-Version: 2.1
Name: espec
Version: 0.1.0.4
Summary: None
Home-page: https://github.com/beidongjiedeguang/festival
Author: K.y
Author-email: beidongjiedeguang@gmail.com
License: MIT
Keywords: Deep Learning,Machine Learning,Neural Networks,Natural Language Processing,Computer Vision
Platform: UNKNOWN
Classifier: Operating System :: OS Independent
Classifier: Intended Audience :: Developers
Classifier: Intended Audience :: Science/Research
Classifier: Topic :: Scientific/Engineering :: Artificial Intelligence
Classifier: Programming Language :: Python :: 3
Classifier: Programming Language :: Python :: 3.5
Classifier: Programming Language :: Python :: 3.6
Classifier: Programming Language :: Python :: 3.7
Requires-Dist: guang
Requires-Dist: python-Levenshtein
Requires-Dist: psutil
Requires-Dist: pretty-errors
Requires-Dist: ephem
Requires-Dist: dill
